{
  "md": {
    "name": "Rahu",
    "start": "2020-01-19T08:57:12",
    "end": "2028-01-19T10:10:31",
    "children": [
      {
        "name": "Moon",
        "years": 1,
        "start": "2020-01-19T08:57:12",
        "end": "2020-04-09T12:59:14.194444",
        "children": [
          {
            "name": "Moon",
            "years": 1,
            "start": "2020-01-19T08:57:12",
            "end": "2020-01-21T15:03:55.394290"
          },
          {
            "name": "Sun",
            "years": 2,
            "start": "2020-01-21T15:03:55.394290",
            "end": "2020-01-28T09:24:05.577160"
          },
          {
            "name": "Jup",
            "years": 3,
            "start": "2020-01-28T09:24:05.577160",
            "end": "2020-02-08T15:57:42.548611"
          },
          {
            "name": "Mars",
            "years": 4,
            "start": "2020-02-08T15:57:42.548611",
            "end": "2020-02-24T10:44:46.308642"
          },
          {
            "name": "Merc",
            "years": 5,
            "start": "2020-02-24T10:44:46.308642",
            "end": "2020-03-15T17:45:16.857253"
          },
          {
            "name": "Sat",
            "years": 6,
            "start": "2020-03-15T17:45:16.857253",
            "end": "2020-04-09T12:59:14.194444"
          },
          {
            "name": "Ven",
            "years": 7,
            "start": "2020-04-09T12:59:14.194444",
            "end": "2020-05-08T20:26:38.320215"
          },
          {
            "name": "Rah",
            "years": 8,
            "start": "2020-05-08T20:26:38.320215",
            "end": "2020-04-09T12:59:14.194444"
          }
        ]
      },
      {
        "name": "Sun",
        "years": 2,
        "start": "2020-04-09T12:59:14.194444",
        "end": "2020-12-09T01:05:20.777778",
        "children": [
          {
            "name": "Moon",
            "years": 1,
            "start": "2020-04-09T12:59:14.194444",
            "end": "2020-04-16T07:19:24.377314"
          },
          {
            "name": "Sun",
            "years": 2,
            "start": "2020-04-16T07:19:24.377314",
            "end": "2020-05-06T14:19:54.925926"
          },
          {
            "name": "Jup",
            "years": 3,
            "start": "2020-05-06T14:19:54.925926",
            "end": "2020-06-09T10:00:45.840277"
          },
          {
            "name": "Mars",
            "years": 4,
            "start": "2020-06-09T10:00:45.840277",
            "end": "2020-07-26T18:21:57.120370"
          },
          {
            "name": "Merc",
            "years": 5,
            "start": "2020-07-26T18:21:57.120370",
            "end": "2020-09-25T15:23:28.766204"
          },
          {
            "name": "Sat",
            "years": 6,
            "start": "2020-09-25T15:23:28.766204",
            "end": "2020-12-09T01:05:20.777778"
          },
          {
            "name": "Ven",
            "years": 7,
            "start": "2020-12-09T01:05:20.777778",
            "end": "2021-03-06T23:27:33.155093"
          },
          {
            "name": "Rah",
            "years": 8,
            "start": "2021-03-06T23:27:33.155093",
            "end": "2020-12-09T01:05:20.777778"
          }
        ]
      },
      {
        "name": "Jup",
        "years": 3,
        "start": "2020-12-09T01:05:20.777778",
        "end": "2022-01-18T21:15:31.750000",
        "children": [
          {
            "name": "Moon",
            "years": 1,
            "start": "2020-12-09T01:05:20.777778",
            "end": "2020-12-20T07:38:57.749229"
          },
          {
            "name": "Sun",
            "years": 2,
            "start": "2020-12-20T07:38:57.749229",
            "end": "2021-01-23T03:19:48.663580"
          },
          {
            "name": "Jup",
            "years": 3,
            "start": "2021-01-23T03:19:48.663580",
            "end": "2021-03-20T12:07:53.520834"
          },
          {
            "name": "Mars",
            "years": 4,
            "start": "2021-03-20T12:07:53.520834",
            "end": "2021-06-07T10:03:12.320988"
          },
          {
            "name": "Merc",
            "years": 5,
            "start": "2021-06-07T10:03:12.320988",
            "end": "2021-09-16T21:05:45.064043"
          },
          {
            "name": "Sat",
            "years": 6,
            "start": "2021-09-16T21:05:45.064043",
            "end": "2022-01-18T21:15:31.750000"
          },
          {
            "name": "Ven",
            "years": 7,
            "start": "2022-01-18T21:15:31.750000",
            "end": "2022-06-14T10:32:32.378858"
          },
          {
            "name": "Rah",
            "years": 8,
            "start": "2022-06-14T10:32:32.378858",
            "end": "2022-01-18T21:15:31.750000"
          }
        ]
      },
      {
        "name": "Mars",
        "years": 4,
        "start": "2022-01-18T21:15:31.750000",
        "end": "2023-08-10T01:29:47.111111",
        "children": [
          {
            "name": "Moon",
            "years": 1,
            "start": "2022-01-18T21:15:31.750000",
            "end": "2022-02-03T16:02:35.510031"
          },
          {
            "name": "Sun",
            "years": 2,
            "start": "2022-02-03T16:02:35.510031",
            "end": "2022-03-23T00:23:46.790123"
          },
          {
            "name": "Jup",
            "years": 3,
            "start": "2022-03-23T00:23:46.790123",
            "end": "2022-06-09T22:19:05.590278"
          },
          {
            "name": "Mars",
            "years": 4,
            "start": "2022-06-09T22:19:05.590278",
            "end": "2022-09-28T09:48:31.910494"
          },
          {
            "name": "Merc",
            "years": 5,
            "start": "2022-09-28T09:48:31.910494",
            "end": "2023-02-17T10:52:05.750772"
          },
          {
            "name": "Sat",
            "years": 6,
            "start": "2023-02-17T10:52:05.750772",
            "end": "2023-08-10T01:29:47.111111"
          },
          {
            "name": "Ven",
            "years": 7,
            "start": "2023-08-10T01:29:47.111111",
            "end": "2024-03-02T05:41:35.991512"
          },
          {
            "name": "Rah",
            "years": 8,
            "start": "2024-03-02T05:41:35.991512",
            "end": "2023-08-10T01:29:47.111111"
          }
        ]
      },
      {
        "name": "Merc",
        "years": 5,
        "start": "2023-08-10T01:29:47.111111",
        "end": "2025-08-09T13:48:06.861111",
        "children": [
          {
            "name": "Moon",
            "years": 1,
            "start": "2023-08-10T01:29:47.111111",
            "end": "2023-08-30T08:30:17.659722"
          },
          {
            "name": "Sun",
            "years": 2,
            "start": "2023-08-30T08:30:17.659722",
            "end": "2023-10-30T05:31:49.305555"
          },
          {
            "name": "Jup",
            "years": 3,
            "start": "2023-10-30T05:31:49.305555",
            "end": "2024-02-08T16:34:22.048611"
          },
          {
            "name": "Mars",
            "years": 4,
            "start": "2024-02-08T16:34:22.048611",
            "end": "2024-06-29T17:37:55.888889"
          },
          {
            "name": "Merc",
            "years": 5,
            "start": "2024-06-29T17:37:55.888889",
            "end": "2024-12-29T08:42:30.826389"
          },
          {
            "name": "Sat",
            "years": 6,
            "start": "2024-12-29T08:42:30.826389",
            "end": "2025-08-09T13:48:06.861111"
          },
          {
            "name": "Ven",
            "years": 7,
            "start": "2025-08-09T13:48:06.861111",
            "end": "2026-04-30T08:54:43.993055"
          },
          {
            "name": "Rah",
            "years": 8,
            "start": "2026-04-30T08:54:43.993055",
            "end": "2025-08-09T13:48:06.861111"
          }
        ]
      },
      {
        "name": "Sat",
        "years": 6,
        "start": "2025-08-09T13:48:06.861111",
        "end": "2028-01-19T10:10:31",
        "children": [
          {
            "name": "Moon",
            "years": 1,
            "start": "2025-08-09T13:48:06.861111",
            "end": "2025-09-03T09:02:04.198302"
          },
          {
            "name": "Sun",
            "years": 2,
            "start": "2025-09-03T09:02:04.198302",
            "end": "2025-11-16T18:43:56.209876"
          },
          {
            "name": "Jup",
            "years": 3,
            "start": "2025-11-16T18:43:56.209876",
            "end": "2026-03-20T18:53:42.895833"
          },
          {
            "name": "Mars",
            "years": 4,
            "start": "2026-03-20T18:53:42.895833",
            "end": "2026-09-10T09:31:24.256173"
          },
          {
            "name": "Merc",
            "years": 5,
            "start": "2026-09-10T09:31:24.256173",
            "end": "2027-04-21T14:37:00.290895"
          },
          {
            "name": "Sat",
            "years": 6,
            "start": "2027-04-21T14:37:00.290895",
            "end": "2028-01-19T10:10:31"
          },
          {
            "name": "Ven",
            "years": 7,
            "start": "2028-01-19T10:10:31",
            "end": "2028-12-06T20:11:56.383488"
          },
          {
            "name": "Rah",
            "years": 8,
            "start": "2028-12-06T20:11:56.383488",
            "end": "2028-01-19T10:10:31"
          }
        ]
      },
      {
        "name": "Ven",
        "years": 7,
        "start": "2028-01-19T10:10:31",
        "end": "2030-12-09T14:36:59.527778",
        "children": [
          {
            "name": "Moon",
            "years": 1,
            "start": "2028-01-19T10:10:31",
            "end": "2028-02-17T17:37:55.125772"
          },
          {
            "name": "Sun",
            "years": 2,
            "start": "2028-02-17T17:37:55.125772",
            "end": "2028-05-15T16:00:07.503086"
          },
          {
            "name": "Jup",
            "years": 3,
            "start": "2028-05-15T16:00:07.503086",
            "end": "2028-10-09T05:17:08.131944"
          },
          {
            "name": "Mars",
            "years": 4,
            "start": "2028-10-09T05:17:08.131944",
            "end": "2029-05-02T09:28:57.012346"
          },
          {
            "name": "Merc",
            "years": 5,
            "start": "2029-05-02T09:28:57.012346",
            "end": "2030-01-21T04:35:34.144290"
          },
          {
            "name": "Sat",
            "years": 6,
            "start": "2030-01-21T04:35:34.144290",
            "end": "2030-12-09T14:36:59.527778"
          },
          {
            "name": "Ven",
            "years": 7,
            "start": "2030-12-09T14:36:59.527778",
            "end": "2031-12-25T15:33:13.162809"
          },
          {
            "name": "Rah",
            "years": 8,
            "start": "2031-12-25T15:33:13.162809",
            "end": "2030-12-09T14:36:59.527778"
          }
        ]
      },
      {
        "name": "Rah",
        "years": 8,
        "start": "2030-12-09T14:36:59.527778",
        "end": "2028-01-19T10:10:31",
        "children": [
          {
            "name": "Moon",
            "years": 1,
            "start": "2030-12-09T14:36:59.527778",
            "end": "2030-11-10T07:09:35.402006"
          },
          {
            "name": "Sun",
            "years": 2,
            "start": "2030-11-10T07:09:35.402006",
            "end": "2030-08-14T08:47:23.024692"
          },
          {
            "name": "Jup",
            "years": 3,
            "start": "2030-08-14T08:47:23.024692",
            "end": "2030-03-20T19:30:22.395834"
          },
          {
            "name": "Mars",
            "years": 4,
            "start": "2030-03-20T19:30:22.395834",
            "end": "2029-08-27T15:18:33.515432"
          },
          {
            "name": "Merc",
            "years": 5,
            "start": "2029-08-27T15:18:33.515432",
            "end": "2028-12-06T20:11:56.383488"
          },
          {
            "name": "Sat",
            "years": 6,
            "start": "2028-12-06T20:11:56.383488",
            "end": "2028-01-19T10:10:31"
          },
          {
            "name": "Ven",
            "years": 7,
            "start": "2028-01-19T10:10:31",
            "end": "2027-01-03T09:14:17.364969"
          },
          {
            "name": "Rah",
            "years": 8,
            "start": "2027-01-03T09:14:17.364969",
            "end": "2028-01-19T10:10:31"
          }
        ]
      }
    ]
  }
}